Metadata-Version: 2.1
Name: efusor
Version: 0.1.2
Summary: Extended Decision Fusion
Home-page: https://github.com/esrel/efusor
Author: Evgeny A. Stepanov
Author-email: stepanov.evgeny.a@gmail.com
Classifier: Development Status :: 3 - Alpha
Requires-Python: >=3.10
License-File: LICENSE
